azure/__init__.py
azure/cli/__init__.py
azure/cli/command_modules/__init__.py
azure/cli/command_modules/role/__init__.py
azure/cli/command_modules/role/_client_factory.py
azure/cli/command_modules/role/_completers.py
azure/cli/command_modules/role/_help.py
azure/cli/command_modules/role/_multi_api_adaptor.py
azure/cli/command_modules/role/_params.py
azure/cli/command_modules/role/_validators.py
azure/cli/command_modules/role/commands.py
azure/cli/command_modules/role/custom.py
azure_cli_role-2.6.4.dist-info/METADATA
azure_cli_role-2.6.4.dist-info/WHEEL
azure_cli_role-2.6.4.dist-info/top_level.txt
azure_cli_role-2.6.4.dist-info/RECORD
