Metadata-Version: 2.1
Name: azure-cli-role
Version: 2.6.4
Summary: Microsoft Azure Command-Line Tools Role Command Module
Home-page: https://github.com/Azure/azure-cli
Author: Microsoft Corporation
Author-email: azpycli@microsoft.com
License: MIT
Platform: UNKNOWN
Classifier: Development Status :: 5 - Production/Stable
Classifier: Intended Audience :: Developers
Classifier: Intended Audience :: System Administrators
Classifier: Programming Language :: Python
Classifier: Programming Language :: Python :: 2
Classifier: Programming Language :: Python :: 2.7
Classifier: Programming Language :: Python :: 3
Classifier: Programming Language :: Python :: 3.4
Classifier: Programming Language :: Python :: 3.5
Classifier: Programming Language :: Python :: 3.6
Classifier: License :: OSI Approved :: MIT License
Requires-Dist: azure-cli-core
Requires-Dist: azure-mgmt-authorization (==0.50.0)
Requires-Dist: azure-mgmt-monitor (==0.5.2)
Requires-Dist: azure-graphrbac (==0.60.0)
Requires-Dist: azure-keyvault (==1.1.0)
Requires-Dist: pytz
Requires-Dist: azure-cli-command-modules-nspkg (>=2.0.0)
